RPTH/__init__.py
RPTH/decode.py
RPTH/encode.py
RPTH/main.py
readablePTH-0.1.4.dist-info/LICENSE
readablePTH-0.1.4.dist-info/METADATA
readablePTH-0.1.4.dist-info/WHEEL
readablePTH-0.1.4.dist-info/entry_points.txt
readablePTH-0.1.4.dist-info/top_level.txt
readablePTH-0.1.4.dist-info/RECORD
