Metadata-Version: 2.1
Name: readablePTH
Version: 0.1.4
Summary: This project can write json file from pth and can write the pth again from the json.
Home-page: https://github.com/oneview-space/readablePTH
Author: OneView
Author-email: ophir@oneview.ai
License: UNKNOWN
Platform: UNKNOWN
Requires-Dist: torch (>=1.6)
Requires-Dist: json-tricks (~=3.15.5)
Requires-Dist: numpy (>=1.18.1)
